MANIFEST.in
README.rst
setup.py
docs/conf.py
docs/index.rst
xbob/__init__.py
xbob.db.frgc.egg-info/PKG-INFO
xbob.db.frgc.egg-info/SOURCES.txt
xbob.db.frgc.egg-info/dependency_links.txt
xbob.db.frgc.egg-info/entry_points.txt
xbob.db.frgc.egg-info/namespace_packages.txt
xbob.db.frgc.egg-info/not-zip-safe
xbob.db.frgc.egg-info/requires.txt
xbob.db.frgc.egg-info/top_level.txt
xbob/db/__init__.py
xbob/db/frgc/__init__.py
xbob/db/frgc/driver.py
xbob/db/frgc/models.py
xbob/db/frgc/query.py
xbob/db/frgc/test.py