Metadata-Version: 1.1
Name: xbob.db.frgc
Version: 1.1.2
Summary: Database Access API of the Face Recognition Grand Challenge (FRGC) ver2.0 image database for Bob
Home-page: http://github.com/bioidiap/xbob.db.frgc
Author: Manuel Guenther
Author-email: manuel.guenther@idiap.ch
License: GPLv3
Platform: UNKNOWN
Classifier: Development Status :: 4 - Beta
Classifier: Intended Audience :: Developers
Classifier: License :: OSI Approved :: GNU General Public License v3 (GPLv3)
Classifier: Natural Language :: English
Classifier: Programming Language :: Python
Classifier: Topic :: Scientific/Engineering :: Artificial Intelligence
Classifier: Topic :: Database :: Front-Ends
